yaramail/__init__.py
yaramail/_cli.py
yara_mail-3.3.0.dist-info/METADATA
yara_mail-3.3.0.dist-info/WHEEL
yara_mail-3.3.0.dist-info/entry_points.txt
yara_mail-3.3.0.dist-info/licenses/LICENSE
yara_mail-3.3.0.dist-info/RECORD
