Metadata-Version: 2.4
Name: yara-mail
Version: 3.3.0
Summary: A Python package and command line utility for scanning emails with YARA rules
Project-URL: Homepage, https://github.com/seanthegeek/yaramail
Project-URL: Documentation, https://seanthegeek.github.io/yaramail/
Project-URL: Issues, https://github.com/seanthegeek/yaramail/issues
Project-URL: Changelog, https://github.com/seanthegeek/yaramail/blob/master/CHANGELOG.md
Author-email: Sean Whalen <whalenster@gmail.com>
License-Expression: Apache-2.0
License-File: LICENSE
Keywords: YARA,email,information security,infosec,security
Classifier: License :: OSI Approved :: Apache Software License
Classifier: Operating System :: OS Independent
Classifier: Programming Language :: Python :: 3
Classifier: Topic :: Communications :: Email
Classifier: Topic :: Security
Requires-Python: >=3.7
Requires-Dist: mailsuite>=1.9.20
Requires-Dist: pdftotext==2.2.2
Requires-Dist: simplejson>=3.17.6
Requires-Dist: yara-python>=4.2.3
